src/__init__.py
src/UA_Lib_jamie_local/__init__.py
src/UA_Lib_jamie_local/db.py
src/UA_Lib_jamie_local/dbot.py
src/UA_Lib_jamie_local/main.py
src/UA_Lib_jamie_local/meme.py
src/UA_Lib_jamie_local/neoinfo.py
src/UA_Lib_jamie_local/uuid.py
Syx_lib-1.0.0.dist-info/LICENSE
Syx_lib-1.0.0.dist-info/METADATA
Syx_lib-1.0.0.dist-info/WHEEL
Syx_lib-1.0.0.dist-info/top_level.txt
Syx_lib-1.0.0.dist-info/RECORD
