Metadata-Version: 2.1
Name: Syx_lib
Version: 1.0.0
Author: jamie.local
License-File: LICENSE
Requires-Dist: requests
Requires-Dist: discord.py
Requires-Dist: psutil
Requires-Dist: importlib-metadata ; python_version < "3.10"
